MANIFEST.in
README.md
setup.cfg
setup.py
solvebio_dash_components/__init__.py
solvebio_dash_components/bundle.js
solvebio_dash_components/bundle.js.map
solvebio_dash_components/metadata.json
solvebio_dash_components/version.py
solvebio_dash_components.egg-info/PKG-INFO
solvebio_dash_components.egg-info/SOURCES.txt
solvebio_dash_components.egg-info/dependency_links.txt
solvebio_dash_components.egg-info/requires.txt
solvebio_dash_components.egg-info/top_level.txt