Metadata-Version: 2.1
Name: solvebio-dash-components
Version: 0.6.3
Summary: The SolveBio Dash components suite
Home-page: https://github.com/solvebio/solvebio-dash-components
Author: Solve, Inc.
Author-email: contact@solvebio.com
License: UNKNOWN
Platform: UNKNOWN
Classifier: Intended Audience :: Science/Research
Classifier: Operating System :: OS Independent
Classifier: Programming Language :: Python
Classifier: Topic :: Software Development :: Libraries :: Python Modules
Classifier: Topic :: Scientific/Engineering :: Bio-Informatics
